harpy/__init__.py
harpy/napari.yaml
harpy/pipeline.py
harpy/single.py
harpy/_tests/__init__.py
harpy/_tests/conftest.py
harpy/_tests/test_notebooks.py
harpy/_tests/test_pipeline.py
harpy/_tests/test_widget.py
harpy/_tests/test_datasets/test_pixie_example.py
harpy/_tests/test_datasets/test_proteomics.py
harpy/_tests/test_datasets/test_transcriptomics.py
harpy/_tests/test_image/test_combine.py
harpy/_tests/test_image/test_contrast.py
harpy/_tests/test_image/test_filters.py
harpy/_tests/test_image/test_manager.py
harpy/_tests/test_image/test_map.py
harpy/_tests/test_image/test_normalize.py
harpy/_tests/test_image/test_rasterize.py
harpy/_tests/test_image/test_transcripts.py
harpy/_tests/test_image/test_pixel_clustering/test_pixel_clustering.py
harpy/_tests/test_image/test_pixel_clustering/test_pixel_clustering_preprocess.py
harpy/_tests/test_image/test_segmentation/test_align_masks.py
harpy/_tests/test_image/test_segmentation/test_expand_labels.py
harpy/_tests/test_image/test_segmentation/test_filter_masks.py
harpy/_tests/test_image/test_segmentation/test_grid.py
harpy/_tests/test_image/test_segmentation/test_map_labels.py
harpy/_tests/test_image/test_segmentation/test_merge_masks.py
harpy/_tests/test_image/test_segmentation/test_segmentation.py
harpy/_tests/test_plot/test_plot.py
harpy/_tests/test_plot/test_plot_annotation.py
harpy/_tests/test_plot/test_plot_cluster.py
harpy/_tests/test_plot/test_plot_flowsom.py
harpy/_tests/test_plot/test_plot_qc_image.py
harpy/_tests/test_plot/test_plot_transcripts.py
harpy/_tests/test_shapes/test_cell_expansion.py
harpy/_tests/test_shapes/test_shape.py
harpy/_tests/test_table/test_allocation.py
harpy/_tests/test_table/test_allocation_intensity.py
harpy/_tests/test_table/test_annotation.py
harpy/_tests/test_table/test_clustering.py
harpy/_tests/test_table/test_filter_on_size.py
harpy/_tests/test_table/test_preprocess.py
harpy/_tests/test_table/test_regionprops.py
harpy/_tests/test_table/test_cell_clustering/test_cell_clustering.py
harpy_analysis-0.2.0.dist-info/METADATA
harpy_analysis-0.2.0.dist-info/WHEEL
harpy_analysis-0.2.0.dist-info/entry_points.txt
harpy_analysis-0.2.0.dist-info/licenses/LICENSE
harpy_analysis-0.2.0.dist-info/RECORD
