Metadata-Version: 2.4
Name: harpy-analysis
Version: 0.2.0
Summary: single-cell spatial proteomics analysis that makes you happy
Project-URL: Bug Tracker, https://github.com/saeyslab/harpy/issues
Project-URL: Documentation, https://github.com/saeyslab/harpy#README.md
Project-URL: Source Code, https://github.com/saeyslab/harpy
Project-URL: User Support, https://github.com/saeyslab/harpy/issues
Author: dambi
License: Academic Non-commercial Software License Agreement
License-File: LICENSE
Classifier: Development Status :: 2 - Pre-Alpha
Classifier: Framework :: napari
Classifier: Intended Audience :: Developers
Classifier: License :: OSI Approved :: BSD License
Classifier: Operating System :: OS Independent
Classifier: Programming Language :: Python
Classifier: Programming Language :: Python :: 3
Classifier: Programming Language :: Python :: 3 :: Only
Classifier: Programming Language :: Python :: 3.10
Classifier: Programming Language :: Python :: 3.11
Classifier: Programming Language :: Python :: 3.12
Classifier: Topic :: Software Development :: Testing
Requires-Python: <3.13,>=3.10
Requires-Dist: crick
Requires-Dist: dask<=2024.11.2,>=2024.4.1
Requires-Dist: datasets>=2.16.0
Requires-Dist: distributed
Requires-Dist: flowsom
Requires-Dist: geopandas>=1.0.1
Requires-Dist: lazy-loader>=0.4
Requires-Dist: leidenalg>=0.9.1
Requires-Dist: magicgui
Requires-Dist: nptyping
Requires-Dist: ome-zarr>=0.9.0
Requires-Dist: omegaconf==2.3.0
Requires-Dist: pyrootutils
Requires-Dist: rasterio>=1.3.2
Requires-Dist: scanpy>=1.9.1
Requires-Dist: seaborn>=0.12.2
Requires-Dist: session-info2
Requires-Dist: spatialdata-io>=0.1.6
Requires-Dist: spatialdata>=0.2.6
Requires-Dist: universal-pathlib
Requires-Dist: voronoi-diagram-for-polygons>=0.1.6
Requires-Dist: xarray-dataclasses>=1.9.1
Requires-Dist: xarray>=2024.10.0
Provides-Extra: basic
Requires-Dist: basicpy>=1.0.0; extra == 'basic'
Requires-Dist: jax>=0.4.6; extra == 'basic'
Requires-Dist: jaxlib>=0.4.6; extra == 'basic'
Provides-Extra: benchmark
Requires-Dist: asv; extra == 'benchmark'
Provides-Extra: cellpose
Requires-Dist: cellpose>=2.2.3; extra == 'cellpose'
Provides-Extra: cli
Requires-Dist: hydra-colorlog>=1.2.0; extra == 'cli'
Requires-Dist: hydra-core>=1.2.0; extra == 'cli'
Requires-Dist: hydra-submitit-launcher>=1.2.0; extra == 'cli'
Requires-Dist: submitit>=1.4.5; extra == 'cli'
Provides-Extra: clustering
Requires-Dist: flowsom; extra == 'clustering'
Requires-Dist: scikit-learn>=1.3.1; extra == 'clustering'
Provides-Extra: dev
Requires-Dist: asv; extra == 'dev'
Requires-Dist: bokeh; extra == 'dev'
Requires-Dist: cellpose>=2.2.3; extra == 'dev'
Requires-Dist: datasets; extra == 'dev'
Requires-Dist: flowsom; extra == 'dev'
Requires-Dist: hydra-colorlog>=1.2.0; extra == 'dev'
Requires-Dist: hydra-core>=1.2.0; extra == 'dev'
Requires-Dist: hydra-submitit-launcher>=1.2.0; extra == 'dev'
Requires-Dist: instanseg-torch>=0.0.8; extra == 'dev'
Requires-Dist: ipython; extra == 'dev'
Requires-Dist: ipywidgets; extra == 'dev'
Requires-Dist: joypy; extra == 'dev'
Requires-Dist: myst-nb; extra == 'dev'
Requires-Dist: napari-spatialdata>=0.2.6; extra == 'dev'
Requires-Dist: napari[all]>=0.4.18; extra == 'dev'
Requires-Dist: nbconvert; extra == 'dev'
Requires-Dist: opencv-python; extra == 'dev'
Requires-Dist: pre-commit; extra == 'dev'
Requires-Dist: pytest; extra == 'dev'
Requires-Dist: pytest-cov; extra == 'dev'
Requires-Dist: pytest-qt; extra == 'dev'
Requires-Dist: scikit-learn>=1.3.1; extra == 'dev'
Requires-Dist: spatialdata-plot<0.2.9; extra == 'dev'
Requires-Dist: sphinx-autodoc-typehints; extra == 'dev'
Requires-Dist: sphinx-book-theme>=1.0.0; extra == 'dev'
Requires-Dist: sphinx-copybutton; extra == 'dev'
Requires-Dist: sphinx-design; extra == 'dev'
Requires-Dist: sphinx-rtd-theme; extra == 'dev'
Requires-Dist: sphinx>=4.5; extra == 'dev'
Requires-Dist: sphinxcontrib-bibtex>=1.0.0; extra == 'dev'
Requires-Dist: squidpy; extra == 'dev'
Requires-Dist: submitit>=1.4.5; extra == 'dev'
Requires-Dist: supervenn>=0.5.0; extra == 'dev'
Requires-Dist: textalloc; extra == 'dev'
Requires-Dist: tox; extra == 'dev'
Requires-Dist: tqdm; extra == 'dev'
Requires-Dist: twine>=4.0.2; extra == 'dev'
Provides-Extra: docs
Requires-Dist: myst-nb; extra == 'docs'
Requires-Dist: sphinx-autodoc-typehints; extra == 'docs'
Requires-Dist: sphinx-book-theme>=1.0.0; extra == 'docs'
Requires-Dist: sphinx-copybutton; extra == 'docs'
Requires-Dist: sphinx-design; extra == 'docs'
Requires-Dist: sphinx-rtd-theme; extra == 'docs'
Requires-Dist: sphinx>=4.5; extra == 'docs'
Requires-Dist: sphinxcontrib-bibtex>=1.0.0; extra == 'docs'
Provides-Extra: extra
Requires-Dist: bokeh; extra == 'extra'
Requires-Dist: cellpose>=2.2.3; extra == 'extra'
Requires-Dist: flowsom; extra == 'extra'
Requires-Dist: hydra-colorlog>=1.2.0; extra == 'extra'
Requires-Dist: hydra-core>=1.2.0; extra == 'extra'
Requires-Dist: hydra-submitit-launcher>=1.2.0; extra == 'extra'
Requires-Dist: instanseg-torch>=0.0.8; extra == 'extra'
Requires-Dist: ipython; extra == 'extra'
Requires-Dist: ipywidgets; extra == 'extra'
Requires-Dist: joypy; extra == 'extra'
Requires-Dist: napari-spatialdata>=0.2.6; extra == 'extra'
Requires-Dist: napari[all]>=0.4.18; extra == 'extra'
Requires-Dist: nbconvert; extra == 'extra'
Requires-Dist: opencv-python; extra == 'extra'
Requires-Dist: scikit-learn>=1.3.1; extra == 'extra'
Requires-Dist: spatialdata-plot<0.2.9; extra == 'extra'
Requires-Dist: squidpy; extra == 'extra'
Requires-Dist: submitit>=1.4.5; extra == 'extra'
Requires-Dist: supervenn>=0.5.0; extra == 'extra'
Requires-Dist: textalloc; extra == 'extra'
Requires-Dist: tqdm; extra == 'extra'
Provides-Extra: instanseg
Requires-Dist: instanseg-torch>=0.0.8; extra == 'instanseg'
Provides-Extra: napari
Requires-Dist: napari-spatialdata>=0.2.6; extra == 'napari'
Requires-Dist: napari[all]>=0.4.18; extra == 'napari'
Provides-Extra: notebook
Requires-Dist: bokeh; extra == 'notebook'
Requires-Dist: ipython; extra == 'notebook'
Requires-Dist: ipywidgets; extra == 'notebook'
Requires-Dist: joypy; extra == 'notebook'
Requires-Dist: nbconvert; extra == 'notebook'
Requires-Dist: spatialdata-plot<0.2.9; extra == 'notebook'
Requires-Dist: supervenn>=0.5.0; extra == 'notebook'
Requires-Dist: textalloc; extra == 'notebook'
Requires-Dist: tqdm; extra == 'notebook'
Provides-Extra: opencv
Requires-Dist: opencv-python; extra == 'opencv'
Provides-Extra: segmentation
Requires-Dist: cellpose>=2.2.3; extra == 'segmentation'
Requires-Dist: instanseg-torch>=0.0.8; extra == 'segmentation'
Provides-Extra: test
Requires-Dist: datasets; extra == 'test'
Requires-Dist: opencv-python; extra == 'test'
Requires-Dist: pytest; extra == 'test'
Requires-Dist: pytest-cov; extra == 'test'
Requires-Dist: pytest-qt; extra == 'test'
Requires-Dist: tox; extra == 'test'
